pyeasyfuse/__init__.py
pyeasyfuse/command_line.py
pyeasyfuse/fusionannotation.py
pyeasyfuse/fusionreadfilter.py
pyeasyfuse/fusiontoolparser.py
pyeasyfuse/fusiontoolparser_helper.py
pyeasyfuse/misc/__init__.py
pyeasyfuse/misc/config.py
pyeasyfuse/misc/count_input_reads.py
pyeasyfuse/misc/io_methods.py
pyeasyfuse/misc/qc_parser.py
pyeasyfuse/misc/queueing.py
pyeasyfuse/processing.py
pyeasyfuse/read_selection.py
pyeasyfuse/ref_data/GTFtoCSV.R
pyeasyfuse/ref_data/__init__.py
pyeasyfuse/ref_data/gff3_to_db.py
pyeasyfuse/ref_data/gtf2tsl.py
pyeasyfuse/ref_data/reformat_genome_fasta.py
pyeasyfuse/requantify.py
pyeasyfuse/resources/R/R_model_prediction.R
pyeasyfuse/resources/model/Fusion_modeling_FFPE_train_v35.random_forest.model_full_data.EF_full.rds
pyeasyfuse/resources/model/Fusion_modeling_FFPE_train_v35.random_forest.model_full_data.EF_full_rep.rds
pyeasyfuse/resources/model/Fusion_modeling_FFPE_train_v35.random_forest.model_full_data.EF_requant.rds
pyeasyfuse/resources/model/Fusion_modeling_FFPE_train_v35.random_forest.model_full_data.EF_requant_type.rds
pyeasyfuse/summarize_data.py
pyeasyfuse/tests/__init__.py
pyeasyfuse/tests/resources/fusioncatcher_1.txt
pyeasyfuse/tests/resources/fusioncatcher_2.txt
pyeasyfuse/tests/resources/infusion.txt
pyeasyfuse/tests/resources/mapsplice.txt
pyeasyfuse/tests/resources/soapfuse.txt
pyeasyfuse/tests/resources/starfusion.txt
pyeasyfuse/tests/resources/test.config.ini
pyeasyfuse/tests/test_config.py
pyeasyfuse/tests/test_fusion_annotation.py
pyeasyfuse/tests/test_fusion_tool_parser.py
pyeasyfuse/tool_wrapper/__init__.py
pyeasyfuse/tool_wrapper/skewer_wrapper.py
pyeasyfuse/tool_wrapper/soapfuse_wrapper.py
pyeasyfuse/tool_wrapper/star_custom_index.py
pyeasyfuse-2.0.3.dist-info/LICENSE
pyeasyfuse-2.0.3.dist-info/METADATA
pyeasyfuse-2.0.3.dist-info/WHEEL
pyeasyfuse-2.0.3.dist-info/entry_points.txt
pyeasyfuse-2.0.3.dist-info/RECORD
